bsxprinter/__init__.py
bsxprinter/formatters.py
bsxprinter/generator.py
bsxprinter-0.4.dist-info/DESCRIPTION.rst
bsxprinter-0.4.dist-info/METADATA
bsxprinter-0.4.dist-info/RECORD
bsxprinter-0.4.dist-info/WHEEL
bsxprinter-0.4.dist-info/metadata.json
bsxprinter-0.4.dist-info/top_level.txt
bsxprinter-0.4.dist-info/zip-safe
