Metadata-Version: 2.0
Name: bsxprinter
Version: 0.4
Summary: BSX Printer Python Lib
Home-page: https://github.com/Kub-AT/bsxprinter-python
Author: UNKNOWN
Author-email: UNKNOWN
License: MIT
Download-URL: https://github.com/Kub-AT/bsxprinter-python/releases
Keywords: bsxprinter thermal posnet novitus
Platform: UNKNOWN
Classifier: Programming Language :: Python
Classifier: Topic :: Software Development :: Libraries
Requires-Dist: lxml (==3.6.4)
Requires-Dist: six (>=1.5)
Provides-Extra: docs
Requires-Dist: numpydoc; extra == 'docs'
Requires-Dist: sphinx (==1.2.3); extra == 'docs'
Requires-Dist: sphinx-rtd-theme; extra == 'docs'
Requires-Dist: sphinxcontrib-napoleon; extra == 'docs'
Provides-Extra: tests
Requires-Dist: nose; extra == 'tests'
Requires-Dist: pytest; extra == 'tests'
Requires-Dist: pytest-cov; extra == 'tests'
Requires-Dist: pytest-pep8; extra == 'tests'
